{
  "Sakaka": {
    "id": "1",
    "name": "Sakaka",
    "city_id": "1",
    "description": "It is located in aljouf city"
  },
  "Dumat aljandal": {
    "id": "2",
    "name": "Dumat aljandal",
    "city_id": "1",
    "description": "It is located in aljouf city"
  },
  "Sawir": {
    "id": "3",
    "name": "Sawir",
    "city_id": "1",
    "description": "It is located in aljouf city"
  },
  "Tabarjal": {
    "id": "4",
    "name": "Tabarjal",
    "city_id": "1",
    "description": "It is located in aljouf city"
  },
  "Qurayyat": {
    "id": "5",
    "name": "Qurayyat",
    "city_id": "1",
    "description": "It is located in aljouf city"
  }
}
